{
    "Objects": [
        {
            "name": "Land_Mil_Fortified_Nest_Small",
            "pos": [
                13366.72265625,
                5.030613422393799,
                6617.21630859375
            ],
            "ypr": [
                -107.99999237060547,
                0.0,
                -0.0
            ]
        },
        {
            "name": "Land_House_1B01_Pub",
            "pos": [
                13424.7001953125,
                9.408559799194336,
                6160.18994140625
            ],
            "ypr": [
                -170.99998474121095,
                0.0,
                0.0
            ]
        },
        {
            "name": "ChernarusMap_Open",
            "pos": [
                13426.900390625,
                7.369999885559082,
                6163.31982421875
            ],
            "ypr": [
                -179.99998474121095,
                85.50001525878906,
                175.5
            ]
        },
        {
            "name": "LongTorch",
            "pos": [
                13422.2001953125,
                7.626510143280029,
                6162.740234375
            ],
            "ypr": [
                6.5,
                -40.999996185302737,
                2.499999761581421
            ]
        },
        {
            "name": "Canteen",
            "pos": [
                13420.5419921875,
                7.600293159484863,
                6162.3046875
            ],
            "ypr": [
                17.999984741210939,
                0.0,
                0.0
            ]
        },
        {
            "name": "Canteen",
            "pos": [
                13420.330078125,
                7.590048789978027,
                6162.375
            ],
            "ypr": [
                17.999984741210939,
                0.0,
                0.0
            ]
        },
        {
            "name": "Canteen",
            "pos": [
                13420.099609375,
                7.6057281494140629,
                6162.47998046875
            ],
            "ypr": [
                2.7595739364624025,
                0.0,
                0.0
            ]
        },
        {
            "name": "BakedBeansCan",
            "pos": [
                13419.677734375,
                7.481159210205078,
                6162.48046875
            ],
            "ypr": [
                0.0,
                -0.0,
                -0.0
            ]
        },
        {
            "name": "BakedBeansCan",
            "pos": [
                13419.5498046875,
                7.480611801147461,
                6162.50537109375
            ],
            "ypr": [
                8.999999046325684,
                -0.0,
                -0.0
            ]
        },
        {
            "name": "BakedBeansCan",
            "pos": [
                13419.4228515625,
                7.480162620544434,
                6162.52294921875
            ],
            "ypr": [
                8.999999046325684,
                -0.0,
                -0.0
            ]
        },
        {
            "name": "BakedBeansCan",
            "pos": [
                13419.2998046875,
                7.4798264503479,
                6162.54052734375
            ],
            "ypr": [
                8.999999046325684,
                -0.0,
                -0.0
            ]
        },
        {
            "name": "Defibrillator",
            "pos": [
                13421.400390625,
                7.880420207977295,
                6162.8798828125
            ],
            "ypr": [
                -172.39999389648438,
                89.18266296386719,
                0.0
            ]
        },
        {
            "name": "Crackers",
            "pos": [
                13420.087890625,
                7.986569404602051,
                6162.5546875
            ],
            "ypr": [
                13.887979507446289,
                0.0,
                0.0
            ]
        },
        {
            "name": "Crackers",
            "pos": [
                13419.9072265625,
                7.989065170288086,
                6162.58154296875
            ],
            "ypr": [
                13.887994766235352,
                0.0,
                0.0
            ]
        },
        {
            "name": "Crackers",
            "pos": [
                13419.7421875,
                7.993105888366699,
                6162.6181640625
            ],
            "ypr": [
                13.887994766235352,
                0.0,
                0.0
            ]
        },
        {
            "name": "Crackers",
            "pos": [
                13419.5703125,
                7.99403715133667,
                6162.62841796875
            ],
            "ypr": [
                13.887994766235352,
                0.0,
                0.0
            ]
        },
        {
            "name": "DisinfectantSpray",
            "pos": [
                13420.900390625,
                7.599029064178467,
                6163.0400390625
            ],
            "ypr": [
                0.0,
                0.0,
                0.0
            ]
        },
        {
            "name": "CigarettePack_Partyzanka",
            "pos": [
                13421.98046875,
                7.368444919586182,
                6165.58740234375
            ],
            "ypr": [
                0.0,
                -0.0,
                -0.0
            ]
        },
        {
            "name": "PetrolLighter",
            "pos": [
                13421.9130859375,
                7.408674240112305,
                6165.68408203125
            ],
            "ypr": [
                0.0,
                -0.0,
                -0.0
            ]
        },
        {
            "name": "CoyoteBag_Brown",
            "pos": [
                13417.2998046875,
                8.060400009155274,
                6164.9501953125
            ],
            "ypr": [
                -82.29999542236328,
                -0.8999999165534973,
                0.0
            ]
        },
        {
            "name": "ImprovisedBag",
            "pos": [
                13417.400390625,
                7.859250068664551,
                6165.4599609375
            ],
            "ypr": [
                -81.00009155273438,
                0.0,
                0.0
            ]
        },
        {
            "name": "AssaultBag_Green",
            "pos": [
                13417.5,
                8.09512996673584,
                6165.97998046875
            ],
            "ypr": [
                -80.99999237060547,
                0.0,
                0.0
            ]
        },
        {
            "name": "SodaCan_Pipsi",
            "pos": [
                13420.517578125,
                7.974794387817383,
                6162.49560546875
            ],
            "ypr": [
                53.99998474121094,
                0.0,
                0.0
            ]
        },
        {
            "name": "SodaCan_Pipsi",
            "pos": [
                13420.447265625,
                7.976200580596924,
                6162.5107421875
            ],
            "ypr": [
                53.99998474121094,
                0.0,
                0.0
            ]
        },
        {
            "name": "SodaCan_Pipsi",
            "pos": [
                13420.376953125,
                7.97598123550415,
                6162.52099609375
            ],
            "ypr": [
                53.99998474121094,
                0.0,
                0.0
            ]
        },
        {
            "name": "SodaCan_Pipsi",
            "pos": [
                13420.2919921875,
                7.975862979888916,
                6162.533203125
            ],
            "ypr": [
                53.99998474121094,
                0.0,
                0.0
            ]
        },
        {
            "name": "Flag_Cannibals",
            "pos": [
                13419.599609375,
                8.760100364685059,
                6162.2998046875
            ],
            "ypr": [
                -83.19998168945313,
                -0.8999999165534973,
                96.19998931884766
            ]
        },
        {
            "name": "MetalPlate",
            "pos": [
                13417.0,
                7.865600109100342,
                6163.669921875
            ],
            "ypr": [
                9.199999809265137,
                0.0,
                87.29999542236328
            ]
        },
        {
            "name": "MetalPlate",
            "pos": [
                13420.7998046875,
                7.920300006866455,
                6167.0400390625
            ],
            "ypr": [
                100.69999694824219,
                0.4999999701976776,
                88.99999237060547
            ]
        },
        {
            "name": "SawedoffIzh43Shotgun",
            "pos": [
                13420.7998046875,
                7.187849998474121,
                6163.27978515625
            ],
            "ypr": [
                9.0,
                1.899999976158142,
                -102.4000015258789
            ]
        },
        {
            "name": "AmmoBox_12gaSlug_10Rnd",
            "pos": [
                13420.2001953125,
                6.6356000900268559,
                6163.41015625
            ],
            "ypr": [
                0.0,
                0.0,
                0.0
            ]
        },
        {
            "name": "AmmoBox_12gaSlug_10Rnd",
            "pos": [
                13420.400390625,
                6.63247013092041,
                6163.39013671875
            ],
            "ypr": [
                0.0,
                0.0,
                0.0
            ]
        },
        {
            "name": "AmmoBox_12gaSlug_10Rnd",
            "pos": [
                13420.2998046875,
                6.6244401931762699,
                6163.39013671875
            ],
            "ypr": [
                0.0,
                0.0,
                0.0
            ]
        },
        {
            "name": "AmmoBox_12gaSlug_10Rnd",
            "pos": [
                13420.5,
                6.6290202140808109,
                6163.3798828125
            ],
            "ypr": [
                0.0,
                0.0,
                0.0
            ]
        },
        {
            "name": "AmmoBox_12gaSlug_10Rnd",
            "pos": [
                13420.599609375,
                6.627810001373291,
                6163.3701171875
            ],
            "ypr": [
                0.0,
                0.0,
                0.0
            ]
        },
        {
            "name": "AmmoBox_12gaSlug_10Rnd",
            "pos": [
                13420.7001953125,
                6.634970188140869,
                6163.35986328125
            ],
            "ypr": [
                0.0,
                0.0,
                0.0
            ]
        },
        {
            "name": "GreatHelm",
            "pos": [
                13418.900390625,
                8.23025131225586,
                6162.6298828125
            ],
            "ypr": [
                36.09999084472656,
                1.9999992847442628,
                15.0
            ]
        },
        {
            "name": "GreatHelm",
            "pos": [
                13420.5,
                8.233449935913086,
                6162.39013671875
            ],
            "ypr": [
                -23.899999618530275,
                3.0,
                15.0
            ]
        },
        {
            "name": "Vodka",
            "pos": [
                13420.2001953125,
                8.377829551696778,
                6162.3701171875
            ],
            "ypr": [
                0.0,
                0.0,
                0.0
            ]
        },
        {
            "name": "Vodka",
            "pos": [
                13420.099609375,
                8.374369621276856,
                6162.39990234375
            ],
            "ypr": [
                0.0,
                0.0,
                0.0
            ]
        },
        {
            "name": "Vodka",
            "pos": [
                13419.2001953125,
                8.364049911499024,
                6162.52001953125
            ],
            "ypr": [
                0.0,
                0.0,
                0.0
            ]
        },
        {
            "name": "Vodka",
            "pos": [
                13419.099609375,
                8.372309684753418,
                6162.55029296875
            ],
            "ypr": [
                0.0,
                0.0,
                0.0
            ]
        },
        {
            "name": "Sword",
            "pos": [
                13419.5,
                8.39033031463623,
                6162.39990234375
            ],
            "ypr": [
                -79.9999008178711,
                -49.999996185302737,
                0.0
            ]
        },
        {
            "name": "Sword",
            "pos": [
                13419.7998046875,
                8.387450218200684,
                6162.330078125
            ],
            "ypr": [
                -84.9999008178711,
                49.999996185302737,
                -2.999999761581421
            ]
        },
        {
            "name": "BookTheRedBadgeOfCourage",
            "pos": [
                13419.7998046875,
                7.372223377227783,
                6166.31982421875
            ],
            "ypr": [
                -180.0,
                -90.0,
                -180.0
            ]
        },
        {
            "name": "Zucchini",
            "pos": [
                13420.4794921875,
                7.13643741607666,
                6163.9765625
            ],
            "ypr": [
                0.0,
                -0.0,
                -0.0
            ]
        },
        {
            "name": "GreenBellPepper",
            "pos": [
                13420.30078125,
                7.079526901245117,
                6163.88134765625
            ],
            "ypr": [
                0.0,
                -0.0,
                -0.0
            ]
        },
        {
            "name": "Tomato",
            "pos": [
                13420.400390625,
                7.174409866333008,
                6164.06982421875
            ],
            "ypr": [
                0.0,
                0.0,
                0.0
            ]
        },
        {
            "name": "Pear",
            "pos": [
                13420.400390625,
                7.114373683929443,
                6163.830078125
            ],
            "ypr": [
                0.0,
                0.0,
                0.09999998658895493
            ]
        },
        {
            "name": "Banana",
            "pos": [
                13420.5146484375,
                7.115761756896973,
                6163.91650390625
            ],
            "ypr": [
                0.0,
                -0.0,
                -0.0
            ]
        },
        {
            "name": "Apple",
            "pos": [
                13420.5205078125,
                7.130314826965332,
                6163.74755859375
            ],
            "ypr": [
                0.0,
                -0.0,
                -0.0
            ]
        },
        {
            "name": "BearTrap",
            "pos": [
                13428.5,
                8.205820083618164,
                6164.35009765625
            ],
            "ypr": [
                -172.39999389648438,
                0.0,
                90.9000015258789
            ]
        },
        {
            "name": "LeatherJacket_Brown",
            "pos": [
                13427.099609375,
                7.347970008850098,
                6161.830078125
            ],
            "ypr": [
                0.0,
                0.0,
                0.0
            ]
        },
        {
            "name": "LeatherPants_Brown",
            "pos": [
                13426.599609375,
                7.385799884796143,
                6161.7998046875
            ],
            "ypr": [
                -170.99998474121095,
                -85.00000762939453,
                -175.0
            ]
        },
        {
            "name": "LeatherShoes_Brown",
            "pos": [
                13426.400390625,
                6.5840301513671879,
                6161.77001953125
            ],
            "ypr": [
                0.0,
                0.0,
                0.0
            ]
        },
        {
            "name": "LeatherHat_Brown",
            "pos": [
                13426.400390625,
                7.489999771118164,
                6161.0400390625
            ],
            "ypr": [
                105.69998931884766,
                -43.900001525878909,
                123.19999694824219
            ]
        },
        {
            "name": "LeatherGloves_Brown",
            "pos": [
                13426.5205078125,
                7.354729175567627,
                6161.43359375
            ],
            "ypr": [
                0.0,
                -0.0,
                -0.0
            ]
        },
        {
            "name": "LeatherSack_Brown",
            "pos": [
                13427.7001953125,
                7.822080135345459,
                6161.52978515625
            ],
            "ypr": [
                104.39998626708985,
                0.0,
                0.0
            ]
        },
        {
            "name": "LeatherBelt_Beige",
            "pos": [
                13427.2001953125,
                7.40984582901001,
                6161.31005859375
            ],
            "ypr": [
                55.29999923706055,
                -85.00000762939453,
                0.0
            ]
        },
        {
            "name": "LeatherStorageVest_Brown",
            "pos": [
                13427.900390625,
                8.005789756774903,
                6162.3798828125
            ],
            "ypr": [
                12.499998092651368,
                0.0,
                -90.0
            ]
        },
        {
            "name": "Mp133Shotgun",
            "pos": [
                13424.447265625,
                7.724135875701904,
                6158.40625
            ],
            "ypr": [
                9.0,
                0.0,
                0.0
            ]
        },
        {
            "name": "Mp133Shotgun",
            "pos": [
                13424.400390625,
                8.034159660339356,
                6158.35986328125
            ],
            "ypr": [
                9.199999809265137,
                0.0,
                0.0
            ]
        },
        {
            "name": "SeaChest",
            "pos": [
                13424.2685546875,
                6.578476428985596,
                6166.18017578125
            ],
            "ypr": [
                98.99993133544922,
                0.0,
                -0.0
            ]
        },
        {
            "name": "SeaChest",
            "pos": [
                13424.2392578125,
                6.5590033531188969,
                6158.4990234375
            ],
            "ypr": [
                -80.71614837646485,
                0.0,
                0.0
            ]
        },
        {
            "name": "Torch",
            "pos": [
                13427.5,
                7.775390148162842,
                6156.60009765625
            ],
            "ypr": [
                53.999996185302737,
                0.0,
                45.0
            ]
        },
        {
            "name": "LongTorch",
            "pos": [
                13426.599609375,
                8.362339973449707,
                6148.58984375
            ],
            "ypr": [
                0.0,
                0.0,
                39.999996185302737
            ]
        },
        {
            "name": "LongTorch",
            "pos": [
                13415.099609375,
                8.218239784240723,
                6150.0498046875
            ],
            "ypr": [
                0.0,
                39.999996185302737,
                0.0
            ]
        },
        {
            "name": "MetalPlate",
            "pos": [
                13425.599609375,
                7.87529993057251,
                6166.39990234375
            ],
            "ypr": [
                -170.99998474121095,
                -90.0,
                -180.0
            ]
        },
        {
            "name": "MetalPlate",
            "pos": [
                13423.099609375,
                7.985569953918457,
                6166.83984375
            ],
            "ypr": [
                -171.6999969482422,
                -90.0,
                -180.0
            ]
        },
        {
            "name": "MetalPlate",
            "pos": [
                13419.0,
                7.885340213775635,
                6167.43994140625
            ],
            "ypr": [
                8.899999618530274,
                -85.09998321533203,
                -0.20000000298023225
            ]
        },
        {
            "name": "MetalPlate",
            "pos": [
                13427.900390625,
                7.877699851989746,
                6160.18994140625
            ],
            "ypr": [
                9.0,
                0.0,
                90.0
            ]
        }
    ]
}